nkkTest/test1.py
nkkTest/test2.py
nkkTest-0.0.0.2.dist-info/METADATA
nkkTest-0.0.0.2.dist-info/WHEEL
nkkTest-0.0.0.2.dist-info/top_level.txt
nkkTest-0.0.0.2.dist-info/RECORD
