Metadata-Version: 2.1
Name: nkkTest
Version: 0.0.0.2
Summary: My First Test package
Home-page: UNKNOWN
Author: nkk
Author-email: llbiss0101@naver.com
License: MIT
Platform: UNKNOWN
Requires-Python: >=3
